Workbook

Sheet 📋 AR Data
A1: Customer ID | B1: Customer Name | C1: Invoice # | D1: Invoice Date | E1: Due Date | F1: Amount ($) | G1: Days Outstanding | H1: Aging Bucket | I1: Last Contact Date | J1: Contact Method | K1: Dispute Flag | L1: Dispute Reason | M1: Account Manager | N1: Region | O1: Priority Score
A2: C001 | B2: TechFlow Solutions | C2: INV-10045 | D2: 2025-01-15 | E2: 2025-02-14 | F2: 12500 | G2: 88 | H2: 61-90 days | I2: 2025-03-10 | J2: Email | K2: No | M2: Sarah Chen | N2: North America | O2: High
A3: C002 | B3: MedSupply Corp | C3: INV-10046 | D3: 2025-01-20 | E3: 2025-02-19 | F3: 47800 | G3: 83 | H3: 61-90 days | I3: 2025-03-05 | J3: Phone | K3: Yes | L3: Price dispute | M3: Mark Torres | N3: LATAM | O3: Critical
A4: C003 | B4: Global Logistics Inc | C4: INV-10047 | D4: 2025-02-01 | E4: 2025-03-03 | F4: 8900 | G4: 70 | H4: 61-90 days | I4: 2025-03-15 | J4: Email | K4: No | M4: Sarah Chen | N4: EMEA | O4: Medium
A5: C004 | B5: Apex Manufacturing | C5: INV-10048 | D5: 2025-02-10 | E5: 2025-03-12 | F5: 125000 | G5: 61 | H5: 61-90 days | I5: 2025-03-20 | J5: Video Call | K5: Yes | L5: Service quality | M5: James Wu | N5: North America | O5: Critical
A6: C005 | B6: SkyNet Retail | C6: INV-10049 | D6: 2025-02-15 | E6: 2025-03-17 | F6: 3200 | G6: 56 | H6: 31-60 days | I6: 2025-03-18 | J6: Email | K6: No | M6: Maria Lopez | N6: LATAM | O6: Low
A7: C006 | B7: Coastal Pharma | C7: INV-10050 | D7: 2025-02-20 | E7: 2025-03-22 | F7: 67400 | G7: 51 | H7: 31-60 days | I7: 2025-03-22 | J7: Phone | K7: No | M7: James Wu | N7: North America | O7: High
A8: C007 | B8: Nexus IT Group | C8: INV-10051 | D8: 2025-02-22 | E8: 2025-03-24 | F8: 15600 | G8: 49 | H8: 31-60 days | I8: 2025-03-24 | J8: Email | K8: No | M8: Sarah Chen | N8: EMEA | O8: Medium
A9: C008 | B9: BuildRight Construction | C9: INV-10052 | D9: 2025-02-25 | E9: 2025-03-27 | F9: 28900 | G9: 46 | H9: 31-60 days | I9: 2025-03-25 | J9: Phone | K9: Yes | L9: Quantity short | M9: Mark Torres | N9: North America | O9: High
A10: C009 | B10: EduTech Academy | C10: INV-10053 | D10: 2025-03-01 | E10: 2025-03-31 | F10: 5400 | G10: 42 | H10: 31-60 days | I10: 2025-03-28 | J10: Email | K10: No | M10: Maria Lopez | N10: LATAM | O10: Low
A11: C010 | B11: Prime Distribution | C11: INV-10054 | D11: 2025-03-05 | E11: 2025-04-04 | F11: 89300 | G11: 38 | H11: 1-30 days | I11: 2025-04-01 | J11: Email | K11: No | M11: James Wu | N11: North America | O11: High
A12: C011 | B12: Horizon Energy | C12: INV-10055 | D12: 2025-03-08 | E12: 2025-04-07 | F12: 42100 | G12: 35 | H12: 1-30 days | K12: No | M12: Sarah Chen | N12: EMEA | O12: Medium
A13: C012 | B13: FastTrack Couriers | C13: INV-10056 | D13: 2025-03-10 | E13: 2025-04-09 | F13: 7800 | G13: 33 | H13: 1-30 days | I13: 2025-04-05 | J13: Email | K13: No | M13: Mark Torres | N13: LATAM | O13: Low
A14: C013 | B14: Alliance Healthcare | C14: INV-10057 | D14: 2025-03-12 | E14: 2025-04-11 | F14: 156000 | G14: 31 | H14: 1-30 days | I14: 2025-04-08 | J14: Video Call | K14: Yes | L14: Contract dispute | M14: James Wu | N14: North America | O14: Critical
A15: C014 | B15: Metro Services LLC | C15: INV-10058 | D15: 2025-03-15 | E15: 2025-04-14 | F15: 19500 | G15: 28 | H15: 1-30 days | K15: No | M15: Maria Lopez | N15: EMEA | O15: Medium
A16: C015 | B16: Quantum Analytics | C16: INV-10059 | D16: 2025-03-18 | E16: 2025-04-17 | F16: 33700 | G16: 25 | H16: 1-30 days | I16: 2025-04-10 | J16: Email | K16: No | M16: Sarah Chen | N16: North America | O16: Medium
A17: C016 | B17: Silver Oak Wines | C17: INV-10060 | D17: 2025-03-20 | E17: 2025-04-19 | F17: 6100 | G17: 23 | H17: 1-30 days | K17: No | M17: Mark Torres | N17: LATAM | O17: Low
A18: C017 | B18: DeltaTech Systems | C18: INV-10061 | D18: 2025-03-22 | E18: 2025-04-21 | F18: 78900 | G18: 21 | H18: 1-30 days | I18: 2025-04-12 | J18: Email | K18: No | M18: James Wu | N18: North America | O18: High
A19: C018 | B19: Pacific Rim Trading | C19: INV-10062 | D19: 2025-03-25 | E19: 2025-04-24 | F19: 14200 | G19: 18 | H19: 1-30 days | K19: No | M19: Sarah Chen | N19: EMEA | O19: Low
A20: C019 | B20: Ironclad Security | C20: INV-10063 | D20: 2025-03-28 | E20: 2025-04-27 | F20: 52300 | G20: 15 | H20: 1-30 days | I20: 2025-04-15 | J20: Phone | K20: No | M20: Maria Lopez | N20: North America | O20: High
A21: C020 | B21: BrightPath Education | C21: INV-10064 | D21: 2025-04-01 | E21: 2025-05-01 | F21: 9800 | G21: 12 | H21: Current | K21: No | M21: Mark Torres | N21: LATAM | O21: Low
A22: C021 | B22: OmniCare Health | C22: INV-10065 | D22: 2025-04-03 | E22: 2025-05-03 | F22: 234500 | G22: 10 | H22: Current | K22: No | M22: James Wu | N22: North America | O22: Critical
A23: C022 | B23: Summit Financial | C23: INV-10066 | D23: 2025-04-05 | E23: 2025-05-05 | F23: 18700 | G23: 8 | H23: Current | K23: No | M23: Sarah Chen | N23: EMEA | O23: Medium
A24: C023 | B24: RedStar Imports | C24: INV-10067 | D24: 2025-01-05 | E24: 2025-02-04 | F24: 38400 | G24: 98 | H24: 91+ days | I24: 2025-02-28 | J24: Phone | K24: Yes | L24: Non-delivery claim | M24: Mark Torres | N24: LATAM | O24: Critical
A25: C024 | B25: Titan Aerospace | C25: INV-10068 | D25: 2025-12-15 | E25: 2026-01-14 | F25: 195000 | G25: 119 | H25: 91+ days | I25: 2025-02-01 | J25: Video Call | K25: Yes | L25: Billing error | M25: James Wu | N25: North America | O25: Critical
A26: C025 | B26: BlueSky Media | C26: INV-10069 | D26: 2025-01-10 | E26: 2025-02-09 | F26: 11200 | G26: 93 | H26: 91+ days | I26: 2025-03-01 | J26: Email | K26: No | M26: Maria Lopez | N26: EMEA | O26: High

Sheet 📊 Aging Summary
A1: AR AGING INTELLIGENCE DASHBOARD
A2: AI-Assisted Collections & Risk Analysis | Generated: May 14, 2026
A4: AGING BUCKET ANALYSIS
A5: Aging Bucket | B5: # Invoices | C5: Total Outstanding ($) | D5: % of AR | E5: # Disputes | F5: Dispute Amount ($) | G5: Risk Level | H5: Action Required
A6: Current | B6: =COUNTIF('📋 AR Data'!H:H,"Current") -> 3 | C6: =SUMIF('📋 AR Data'!H:H,"Current",'📋 AR Data'!F:F) -> 263000 | D6: =C6/C10 -> 1.0752249 | E6: =COUNTIFS('📋 AR Data'!H:H,"Current",'📋 AR Data'!K:K,"Yes") -> 0 | F6: =SUMIFS('📋 AR Data'!F:F,'📋 AR Data'!H:H,"Current",'📋 AR Data'!K:K,"Yes") -> 0 | G6: ✅ Low | H6: Monitor — no immediate action
A7: 1-30 Days | B7: =COUNTIF('📋 AR Data'!H:H,"1-30 days") -> 10 | C7: =SUMIF('📋 AR Data'!H:H,"1-30 days",'📋 AR Data'!F:F) -> 499900 | D7: =C7/C10 -> 2.0437449 | E7: =COUNTIFS('📋 AR Data'!H:H,"1-30 days",'📋 AR Data'!K:K,"Yes") -> 1 | F7: =SUMIFS('📋 AR Data'!F:F,'📋 AR Data'!H:H,"1-30 days",'📋 AR Data'!K:K,"Yes") -> 156000 | G7: 🟡 Medium | H7: Send courtesy reminder — automated
A8: 31-60 Days | B8: =COUNTIF('📋 AR Data'!H:H,"31-60 days") -> 5 | C8: =SUMIF('📋 AR Data'!H:H,"31-60 days",'📋 AR Data'!F:F) -> 120500 | D8: =C8/C10 -> 0.49264105 | E8: =COUNTIFS('📋 AR Data'!H:H,"31-60 days",'📋 AR Data'!K:K,"Yes") -> 1 | F8: =SUMIFS('📋 AR Data'!F:F,'📋 AR Data'!H:H,"31-60 days",'📋 AR Data'!K:K,"Yes") -> 28900 | G8: 🟠 High | H8: Direct outreach — escalate disputes
A9: 61-90 Days | B9: =COUNTIF('📋 AR Data'!H:H,"61-90 days") -> 4 | C9: =SUMIF('📋 AR Data'!H:H,"61-90 days",'📋 AR Data'!F:F) -> 194200 | D9: =C9/C10 -> 0.7939493 | E9: =COUNTIFS('📋 AR Data'!H:H,"61-90 days",'📋 AR Data'!K:K,"Yes") -> 2 | F9: =SUMIFS('📋 AR Data'!F:F,'📋 AR Data'!H:H,"61-90 days",'📋 AR Data'!K:K,"Yes") -> 172800 | G9: 🔴 Critical | H9: Immediate call + legal review
A10: 91+ Days | B10: =COUNTIF('📋 AR Data'!H:H,"91+ days") -> 3 | C10: =SUMIF('📋 AR Data'!H:H,"91+ days",'📋 AR Data'!F:F) -> 244600 | D10: =C10/C10 -> 1 | E10: =COUNTIFS('📋 AR Data'!H:H,"91+ days",'📋 AR Data'!K:K,"Yes") -> 2 | F10: =SUMIFS('📋 AR Data'!F:F,'📋 AR Data'!H:H,"91+ days",'📋 AR Data'!K:K,"Yes") -> 233400 | G10: 💀 Write-off Risk | H10: Escalate to collections/legal NOW
A11: TOTAL | B11: =SUM(B6:B10) -> 25 | C11: =SUM(C6:C10) -> 1322200 | D11: 100% | E11: =SUM(E6:E10) -> 6 | F11: =SUM(F6:F10) -> 591100
A13: KEY PERFORMANCE INDICATORS
A14: Total AR ($) | B14: Total Invoices | C14: Disputed ($) | D14: Dispute Rate | E14: Critical Accounts | F14: Avg Days Outstanding | G14: At-Risk % | H14: DSO (Est.)
A15: =C11 -> 1322200 | B15: =B11 -> 25 | C15: =F11 -> 591100 | D15: =F11/C11 -> 0.44705793 | E15: =COUNTIF('📋 AR Data'!O:O,"Critical") -> 6 | F15: =AVERAGE('📋 AR Data'!G2:G26) -> 46.12 | G15: =(C9+C10)/C11 -> 0.33187112 | H15: =G14/C11*30 -> #VALUE!
A17: BY REGION | F17: BY ACCOUNT MANAGER
A18: Region | B18: # Invoices | C18: Total ($) | D18: % of AR | F18: Account Manager | G18: # Invoices | H18: Total ($)
A19: North America | B19: =COUNTIF('📋 AR Data'!N:N,"North America") -> 11 | C19: =SUMIF('📋 AR Data'!N:N,"North America",'📋 AR Data'!F:F) -> 1073500 | D19: =C19/C11 -> 0.8119044 | F19: Sarah Chen | G19: =COUNTIF('📋 AR Data'!M:M,"Sarah Chen") -> 7 | H19: =SUMIF('📋 AR Data'!M:M,"Sarah Chen",'📋 AR Data'!F:F) -> 145700
A20: LATAM | B20: =COUNTIF('📋 AR Data'!N:N,"LATAM") -> 7 | C20: =SUMIF('📋 AR Data'!N:N,"LATAM",'📋 AR Data'!F:F) -> 118500 | D20: =C20/C11 -> 0.089623355 | F20: Mark Torres | G20: =COUNTIF('📋 AR Data'!M:M,"Mark Torres") -> 6 | H20: =SUMIF('📋 AR Data'!M:M,"Mark Torres",'📋 AR Data'!F:F) -> 138800
A21: EMEA | B21: =COUNTIF('📋 AR Data'!N:N,"EMEA") -> 7 | C21: =SUMIF('📋 AR Data'!N:N,"EMEA",'📋 AR Data'!F:F) -> 130200 | D21: =C21/C11 -> 0.098472243 | F21: James Wu | G21: =COUNTIF('📋 AR Data'!M:M,"James Wu") -> 7 | H21: =SUMIF('📋 AR Data'!M:M,"James Wu",'📋 AR Data'!F:F) -> 946100
A22: TOTAL | B22: =SUM(B19:B21) -> 25 | C22: =SUM(C19:C21) -> 1322200 | D22: 100% | F22: Maria Lopez | G22: =COUNTIF('📋 AR Data'!M:M,"Maria Lopez") -> 5 | H22: =SUMIF('📋 AR Data'!M:M,"Maria Lopez",'📋 AR Data'!F:F) -> 91600

Sheet 🎯 Collections Priority
A1: AI-ASSISTED COLLECTIONS PRIORITY LIST
A2: ⚡ Ranked by Priority Score · Dispute Status · Days Outstanding · Amount at Risk
A3: Priority | B3: Customer Name | C3: Invoice # | D3: Amount ($) | E3: Days Out | F3: Aging Bucket | G3: Dispute | H3: Account Mgr | I3: AI Recommended Action | J3: Next Step Deadline
A4: 1 | B4: Titan Aerospace | C4: INV-10068 | D4: 195000 | E4: 119 | F4: 91+ days | G4: Yes | H4: James Wu | I4: 🚨 ESCALATE TO LEGAL — 119 days outstanding. Billing error dispute open. Schedule executive video call within 24hrs. Prepare credit memo if error confirmed. | J4: IMMEDIATE
A5: 2 | B5: Alliance Healthcare | C5: INV-10057 | D5: 156000 | E5: 31 | F5: 1-30 days | G5: Yes | H5: James Wu | I5: 🚨 CONTRACT DISPUTE — $156K at risk. Early intervention critical before aging worsens. Loop in Sales VP and Legal. Propose mediation call this week. | J5: 48 HOURS
A6: 3 | B6: Apex Manufacturing | C6: INV-10048 | D6: 125000 | E6: 61 | F6: 61-90 days | G6: Yes | H6: James Wu | I6: 🔴 SERVICE DISPUTE — 61 days + service quality complaint. Risk of write-off escalating. Assign senior collector. Offer partial credit to unlock payment. | J6: 72 HOURS
A7: 4 | B7: OmniCare Health | C7: INV-10065 | D7: 234500 | E7: 10 | F7: Current | G7: No | H7: James Wu | I7: ⚠️ LARGEST BALANCE — Current but monitor closely. No contact made yet. Send proactive relationship check-in. Confirm PO and payment terms alignment. | J7: 2 WEEKS
A8: 5 | B8: RedStar Imports | C8: INV-10067 | D8: 38400 | E8: 98 | F8: 91+ days | G8: Yes | H8: Mark Torres | I8: 🚨 NON-DELIVERY CLAIM — 98 days + dispute. Verify delivery records immediately. If confirmed delivered, send proof and demand payment. If not, issue credit. | J8: IMMEDIATE
A9: 6 | B9: MedSupply Corp | C9: INV-10046 | D9: 47800 | E9: 83 | F9: 61-90 days | G9: Yes | H9: Mark Torres | I9: 🔴 PRICE DISPUTE — Request pricing contract. If error: issue corrected invoice. If correct: provide documentation + payment plan for remaining balance. | J9: 48 HOURS
A10: 7 | B10: BlueSky Media | C10: INV-10069 | D10: 11200 | E10: 93 | F10: 91+ days | G10: No | H10: Maria Lopez | I10: 🔴 91+ DAYS — No dispute but no payment. Escalate to collections agency if no response within 5 days. Send final demand letter today. | J10: 5 DAYS
A11: 8 | B11: TechFlow Solutions | C11: INV-10045 | D11: 12500 | E11: 88 | F11: 61-90 days | G11: No | H11: Sarah Chen | I11: 🟠 FOLLOW-UP REQUIRED — 88 days, no dispute. Third reminder call. Offer structured payment plan (50% now + 50% in 30 days). Document commitment in writing. | J11: 3 DAYS
A12: 9 | B12: Coastal Pharma | C12: INV-10050 | D12: 67400 | E12: 51 | F12: 31-60 days | G12: No | H12: James Wu | I12: 🟠 PROACTIVE OUTREACH — $67K approaching critical zone. Send personalized email with payment options. Confirm invoice receipt and PO match. | J12: 1 WEEK
A13: 10 | B13: BuildRight Construction | C13: INV-10052 | D13: 28900 | E13: 46 | F13: 31-60 days | G13: Yes | H13: Mark Torres | I13: 🟠 QUANTITY DISPUTE — Verify delivery note vs invoice. If short-delivered: issue partial credit. If correct: send proof. Request payment for undisputed portion. | J13: 5 DAYS
A14: 11 | B14: Prime Distribution | C14: INV-10054 | D14: 89300 | E14: 38 | F14: 1-30 days | G14: No | H14: James Wu | I14: 🟡 MONITOR — $89K approaching 30-day mark. Send courtesy reminder. High-value account — personal touch preferred over automated email. | J14: 10 DAYS
A15: 12 | B15: Ironclad Security | C15: INV-10063 | D15: 52300 | E15: 15 | F15: 1-30 days | G15: No | H15: Maria Lopez | I15: 🟡 COURTESY REMINDER — Send automated reminder. No action needed yet unless no read receipt. | J15: 2 WEEKS
A16: 13 | B16: DeltaTech Systems | C16: INV-10061 | D16: 78900 | E16: 21 | F16: 1-30 days | G16: No | H16: James Wu | I16: 🟡 MONITOR — Large balance, early stage. Confirm delivery acknowledgment on file. Flag for priority follow-up at 30-day mark. | J16: 2 WEEKS

Sheet 💰 Cash Forecast
A1: 30-DAY CASH RECOVERY FORECAST
A2: AI-estimated recovery probability by bucket based on historical collection patterns
A4: RECOVERY RATE ASSUMPTIONS (Adjustable — Blue = Input)
A5: Bucket | B5: Recovery Rate % | C5: Rationale
A6: Current | B6: 0.95 | C6: Industry benchmark — high likelihood
A7: 1-30 Days | B7: 0.85 | C7: Minor delays expected — still collectible
A8: 31-60 Days | B8: 0.65 | C8: Requires active outreach — moderate risk
A9: 61-90 Days | B9: 0.4 | C9: High risk — disputes likely to delay
A10: 91+ Days | B10: 0.2 | C10: Write-off risk — legal/collections likely
A13: PROJECTED CASH RECOVERY — NEXT 30 DAYS
A14: Aging Bucket | B14: Total AR ($) | C14: Recovery Rate | D14: Expected Recovery ($) | E14: At-Risk ($) | F14: Dispute Exposure ($) | G14: Net Collectible ($)
A15: Current | B15: =SUMIF('📋 AR Data'!H:H,"Current",'📋 AR Data'!F:F) -> 263000 | C15: =B6 -> 0.95 | D15: =B15*C15 -> 249850 | E15: =B15-D15 -> 13150 | F15: =SUMIFS('📋 AR Data'!F:F,'📋 AR Data'!H:H,"Current",'📋 AR Data'!K:K,"Yes") -> 0 | G15: =D15-F15 -> 249850
A16: 1-30 Days | B16: =SUMIF('📋 AR Data'!H:H,"1-30 days",'📋 AR Data'!F:F) -> 499900 | C16: =B7 -> 0.85 | D16: =B16*C16 -> 424915 | E16: =B16-D16 -> 74985 | F16: =SUMIFS('📋 AR Data'!F:F,'📋 AR Data'!H:H,"1-30 days",'📋 AR Data'!K:K,"Yes") -> 156000 | G16: =D16-F16 -> 268915
A17: 31-60 Days | B17: =SUMIF('📋 AR Data'!H:H,"31-60 days",'📋 AR Data'!F:F) -> 120500 | C17: =B8 -> 0.65 | D17: =B17*C17 -> 78325 | E17: =B17-D17 -> 42175 | F17: =SUMIFS('📋 AR Data'!F:F,'📋 AR Data'!H:H,"31-60 Days",'📋 AR Data'!K:K,"Yes") -> 28900 | G17: =D17-F17 -> 49425
A18: 61-90 Days | B18: =SUMIF('📋 AR Data'!H:H,"61-90 days",'📋 AR Data'!F:F) -> 194200 | C18: =B9 -> 0.4 | D18: =B18*C18 -> 77680 | E18: =B18-D18 -> 116520 | F18: =SUMIFS('📋 AR Data'!F:F,'📋 AR Data'!H:H,"61-90 Days",'📋 AR Data'!K:K,"Yes") -> 172800 | G18: =D18-F18 -> -95120
A19: 91+ Days | B19: =SUMIF('📋 AR Data'!H:H,"91+ days",'📋 AR Data'!F:F) -> 244600 | C19: =B10 -> 0.2 | D19: =B19*C19 -> 48920 | E19: =B19-D19 -> 195680 | F19: =SUMIFS('📋 AR Data'!F:F,'📋 AR Data'!H:H,"91+ Days",'📋 AR Data'!K:K,"Yes") -> 233400 | G19: =D19-F19 -> -184480
A20: TOTAL | B20: =SUM(B15:B19) -> 1322200 | D20: =SUM(D15:D19) -> 879690 | E20: =SUM(E15:E19) -> 442510 | F20: =SUM(F15:F19) -> 591100 | G20: =SUM(G15:G19) -> 288590
A22: 💡 AI INSIGHT: Focus collections effort on 61-90 day bucket — highest ROI per hour of collector time. Disputes in 91+ days require legal review before further calls.

Sheet 📝 Executive Summary
A1: WEEKLY AR EXECUTIVE SUMMARY
A2: Auto-Generated from AR Data | Prepared by: Joel Solís | May 14, 2026
A4: 📊 PORTFOLIO OVERVIEW
A5: ▸ Total AR Outstanding | C5: ='📊 Aging Summary'!C15 -> 591100 | D5: Full portfolio value
A6: ▸ Total Invoices | C6: ='📊 Aging Summary'!B15 -> 25 | D6: Active invoice count
A7: ▸ Projected 30-Day Recovery | C7: ='💰 Cash Forecast'!D20 -> 879690 | D7: Based on AI recovery rates
A8: ▸ Total At-Risk Amount | C8: ='💰 Cash Forecast'!E20 -> 442510 | D8: Expected non-recovery
A9: ▸ Total Dispute Exposure | C9: ='📊 Aging Summary'!F15 -> 46.12 | D9: Actively disputed invoices
A11: 🚨 CRITICAL ACTIONS — THIS WEEK
A12: 1. Titan Aerospace (INV-10068) | C12: $195,000 — 119 days — Billing error dispute — LEGAL ESCALATION REQUIRED
A13: 2. Alliance Healthcare (INV-10057) | C13: $156,000 — 31 days — Contract dispute — EXEC INTERVENTION THIS WEEK
A14: 3. RedStar Imports (INV-10067) | C14: $38,400 — 98 days — Non-delivery claim — VERIFY DELIVERY RECORDS TODAY
A15: 4. Apex Manufacturing (INV-10048) | C15: $125,000 — 61 days — Service dispute — SENIOR COLLECTOR ASSIGNED
A17: 💡 AI-GENERATED INSIGHTS & RECOMMENDATIONS
A18: • James Wu manages 5 of the top 6 highest-value at-risk accounts — consider redistributing load or escalating support.
A19: • 91+ day bucket represents 3 invoices but disproportionate write-off risk — legal review recommended before further collector calls.
A20: • 61-90 day bucket has highest ROI for active collections effort — prioritize this bucket for this week's outreach campaign.
A21: • OmniCare Health ($234,500 — Current) is the largest single balance with no contact logged — proactive outreach recommended immediately.
A22: • Dispute rate across portfolio is elevated in 61-90 day range — review billing process for systematic errors causing short payments.
A24: This summary is auto-generated from live AR data. All figures pull dynamically from the AR Data tab. Adjust recovery rate assumptions in 💰 Cash Forecast to model different scenarios.
